sf_label_skew/__init__.py
sf_label_skew/skewing.py
sf_label_skew-0.1.0.dist-info/METADATA
sf_label_skew-0.1.0.dist-info/WHEEL
sf_label_skew-0.1.0.dist-info/top_level.txt
sf_label_skew-0.1.0.dist-info/RECORD
