Metadata-Version: 2.4
Name: sf_label_skew
Version: 0.1.0
Summary: Same Features, Different Label Skew Generator using KMeans and Davies-Bouldin
Author: Your Name
Requires-Python: >=3.6
Requires-Dist: pandas
Requires-Dist: matplotlib
Requires-Dist: scikit-learn
Dynamic: author
Dynamic: requires-dist
Dynamic: requires-python
Dynamic: summary
